LICENSE
README.md
setup.py
v6jail/__init__.py
v6jail/cli.py
v6jail/config.py
v6jail/counter.py
v6jail/ddns.py
v6jail/host.py
v6jail/ini_encoder.py
v6jail/jail.py
v6jail/jailparam.py
v6jail/util.py
v6jail.egg-info/PKG-INFO
v6jail.egg-info/SOURCES.txt
v6jail.egg-info/dependency_links.txt
v6jail.egg-info/requires.txt
v6jail.egg-info/top_level.txt